[
  {
    "event_id": "8af4aa9cf12e",
    "title": "What we know about the Israel-Lebanon ceasefire",
    "location": "伊朗",
    "first_seen_time": "2026-04-17T08:10:00+00:00",
    "last_updated_time": "2026-04-17T14:56:15+00:00",
    "current_status": "ceasefire",
    "trend": "improving",
    "confidence": 90,
    "source_count": 4,
    "source": "德国之声",
    "link": "https://www.dw.com/zh/美伊談判現轉機？川普稱伊朗同意交出核材料/a-76819529?maca=chi-rss-chi-all-1127-xml-mrss",
    "lang": "zh"
  },
  {
    "event_id": "fe62b3df99c0",
    "title": "Strait of Hormuz closed again, Iran says, as ships attacked",
    "location": "霍尔木兹海峡",
    "first_seen_time": "2026-04-12T09:00:00+00:00",
    "last_updated_time": "2026-04-18T21:19:46+00:00",
    "current_status": "ceasefire",
    "trend": "improving",
    "confidence": 90,
    "source_count": 3,
    "source": "德国之声",
    "link": "https://www.dw.com/zh/国际航协：即便海峡重新开放-航油供应恢复仍需数月/a-76710208?maca=chi-rss-chi-all-1127-xml-mrss",
    "lang": "zh"
  },
  {
    "event_id": "488d96d3285c",
    "title": "Israel and Hezbollah continue attacks after Israel-Lebanon talks in US",
    "location": "以色列",
    "first_seen_time": "2026-04-15T14:15:50+00:00",
    "last_updated_time": "2026-04-15T14:15:50+00:00",
    "current_status": "active_conflict",
    "trend": "improving",
    "confidence": 90,
    "source_count": 1,
    "source": "BBC中东",
    "link": "https://www.bbc.com/news/articles/c87ww2z0z3zo?at_medium=RSS&at_campaign=rss",
    "lang": "en"
  },
  {
    "event_id": "1c1565848ae3",
    "title": "霍爾木茲海峽開了又關　輪船報告遭伊朗槍擊　英法介入採取「防禦行動」",
    "location": "霍尔木兹海峡",
    "first_seen_time": "2026-04-15T08:10:22+00:00",
    "last_updated_time": "2026-04-19T04:02:26+00:00",
    "current_status": "active_conflict",
    "trend": "stable",
    "confidence": 80,
    "source_count": 4,
    "source": "BBC中文",
    "link": "https://www.bbc.com/zhongwen/articles/cp8444l85yro/trad?at_medium=RSS&at_campaign=rss",
    "lang": "zh"
  },
  {
    "event_id": "4b83b51e3a8f",
    "title": "美國封鎖霍爾木茲海峽 逼中國坐上談判桌？",
    "location": "伊朗·德黑兰",
    "first_seen_time": "2026-04-15T06:31:00+00:00",
    "last_updated_time": "2026-04-15T06:31:00+00:00",
    "current_status": "active_conflict",
    "trend": "stable",
    "confidence": 80,
    "source_count": 1,
    "source": "德国之声",
    "link": "https://www.dw.com/zh/美國封鎖霍爾木茲海峽-逼中國坐上談判桌？/a-76785198?maca=chi-rss-chi-all-1127-xml-mrss",
    "lang": "zh"
  },
  {
    "event_id": "5813870f05b6",
    "title": "French peacekeeper killed in southern Lebanon",
    "location": "伊朗",
    "first_seen_time": "2026-04-19T03:14:45+00:00",
    "last_updated_time": "2026-04-19T03:14:45+00:00",
    "current_status": "active_conflict",
    "trend": "stable",
    "confidence": 80,
    "source_count": 1,
    "source": "BBC中东",
    "link": "https://www.bbc.com/news/articles/cvg4mrm2vm0o?at_medium=RSS&at_campaign=rss",
    "lang": "en"
  },
  {
    "event_id": "47be269c3e54",
    "title": "BBC記者經陸路前往德黑蘭  脆弱停火協議下的伊朗現場採訪記",
    "location": "伊朗·德黑兰",
    "first_seen_time": "2026-04-16T03:53:57+00:00",
    "last_updated_time": "2026-04-16T03:53:57+00:00",
    "current_status": "ceasefire",
    "trend": "improving",
    "confidence": 75,
    "source_count": 1,
    "source": "BBC中文",
    "link": "https://www.bbc.com/zhongwen/articles/ce8lpe2le5vo/trad?at_medium=RSS&at_campaign=rss",
    "lang": "zh"
  },
  {
    "event_id": "d3e1900407e3",
    "title": "伊朗斥美屡次失信 霍尔木兹海峡开而复封",
    "location": "霍尔木兹海峡",
    "first_seen_time": "2026-04-18T10:39:00+00:00",
    "last_updated_time": "2026-04-18T10:39:00+00:00",
    "current_status": "shipping_disrupted",
    "trend": "stable",
    "confidence": 70,
    "source_count": 2,
    "source": "德国之声",
    "link": "https://www.dw.com/zh/伊朗斥美屡次失信-霍尔木兹海峡开而复封/a-76841508?maca=chi-rss-chi-all-1127-xml-mrss",
    "lang": "zh"
  },
  {
    "event_id": "8c170a4ac3ed",
    "title": "IEA 警告：欧洲航油储备“仅剩六周”",
    "location": "霍尔木兹海峡",
    "first_seen_time": "2026-04-17T12:42:00+00:00",
    "last_updated_time": "2026-04-17T12:42:00+00:00",
    "current_status": "partially_restored",
    "trend": "improving",
    "confidence": 70,
    "source_count": 1,
    "source": "德国之声",
    "link": "https://www.dw.com/zh/iea-警告：欧洲航油储备-仅剩六周/a-76830377?maca=chi-rss-chi-all-1127-xml-mrss",
    "lang": "zh"
  },
  {
    "event_id": "01791006d51d",
    "title": "BBC reports from Lebanese border town as residents try to return home",
    "location": "以色列",
    "first_seen_time": "2026-04-18T11:47:11+00:00",
    "last_updated_time": "2026-04-18T11:47:11+00:00",
    "current_status": "ceasefire",
    "trend": "improving",
    "confidence": 70,
    "source_count": 2,
    "source": "BBC中东",
    "link": "https://www.bbc.com/news/videos/cly90z9g5q3o?at_medium=RSS&at_campaign=rss",
    "lang": "en"
  }
]