{
  "markets": {
    "brent": {
      "current": 100.86000061035156,
      "day_change_pct": -1.33,
      "war_change_pct": 29.74,
      "dates": [
        "02/12",
        "02/13",
        "02/17",
        "02/18",
        "02/19",
        "02/20",
        "02/23",
        "02/24",
        "02/25",
        "02/26",
        "02/27",
        "03/02",
        "03/03",
        "03/04",
        "03/05",
        "03/06",
        "03/09",
        "03/10",
        "03/11",
        "03/12",
        "03/13",
        "03/16",
        "03/17",
        "03/18",
        "03/19",
        "03/20",
        "03/23",
        "03/24",
        "03/25",
        "03/26"
      ],
      "prices": [
        67.52,
        67.75,
        67.42,
        70.35,
        71.66,
        71.76,
        71.49,
        70.77,
        70.85,
        70.75,
        72.48,
        77.74,
        81.4,
        81.4,
        85.41,
        92.69,
        98.96,
        87.8,
        91.98,
        100.46,
        103.14,
        100.21,
        103.42,
        107.38,
        108.65,
        112.19,
        99.94,
        104.49,
        102.22,
        100.86
      ],
      "updated": "2026-03-27T03:52:22.426472"
    },
    "wti": {
      "current": 93.52999877929688,
      "day_change_pct": 3.55,
      "war_change_pct": 31.31,
      "dates": [
        "02/12",
        "02/13",
        "02/17",
        "02/18",
        "02/19",
        "02/20",
        "02/23",
        "02/24",
        "02/25",
        "02/26",
        "02/27",
        "03/02",
        "03/03",
        "03/04",
        "03/05",
        "03/06",
        "03/09",
        "03/10",
        "03/11",
        "03/12",
        "03/13",
        "03/16",
        "03/17",
        "03/18",
        "03/19",
        "03/20",
        "03/23",
        "03/24",
        "03/25",
        "03/26"
      ],
      "prices": [
        62.84,
        62.89,
        62.33,
        65.19,
        66.43,
        66.39,
        66.31,
        65.63,
        65.42,
        65.21,
        67.02,
        71.23,
        74.56,
        74.66,
        81.01,
        90.9,
        94.77,
        83.45,
        87.25,
        95.73,
        98.71,
        93.5,
        96.21,
        96.32,
        96.14,
        98.32,
        88.13,
        92.35,
        90.32,
        93.53
      ],
      "updated": "2026-03-27T03:52:22.502324"
    },
    "gold": {
      "current": 4434.10009765625,
      "day_change_pct": -2.54,
      "war_change_pct": -16.25,
      "dates": [
        "02/12",
        "02/13",
        "02/17",
        "02/18",
        "02/19",
        "02/20",
        "02/23",
        "02/24",
        "02/25",
        "02/26",
        "02/27",
        "03/02",
        "03/03",
        "03/04",
        "03/05",
        "03/06",
        "03/09",
        "03/10",
        "03/11",
        "03/12",
        "03/13",
        "03/16",
        "03/17",
        "03/18",
        "03/19",
        "03/20",
        "03/23",
        "03/24",
        "03/25",
        "03/26"
      ],
      "prices": [
        4923.7,
        5022.0,
        4882.9,
        4986.5,
        4975.9,
        5059.3,
        5204.7,
        5155.8,
        5206.4,
        5176.5,
        5230.5,
        5294.4,
        5107.4,
        5120.2,
        5065.3,
        5146.1,
        5091.5,
        5229.7,
        5167.4,
        5115.8,
        5052.5,
        4994.0,
        5001.0,
        4889.9,
        4600.7,
        4570.4,
        4404.1,
        4399.3,
        4549.8,
        4434.1
      ],
      "updated": "2026-03-27T03:52:22.580358"
    },
    "usd_cny": {
      "current": 6.913000106811523,
      "day_change_pct": 0.17,
      "war_change_pct": 0.8,
      "dates": [
        "02/16",
        "02/17",
        "02/18",
        "02/19",
        "02/20",
        "02/23",
        "02/24",
        "02/25",
        "02/26",
        "02/27",
        "03/02",
        "03/03",
        "03/04",
        "03/05",
        "03/06",
        "03/09",
        "03/10",
        "03/11",
        "03/12",
        "03/13",
        "03/16",
        "03/17",
        "03/18",
        "03/19",
        "03/20",
        "03/23",
        "03/24",
        "03/25",
        "03/26",
        "03/27"
      ],
      "prices": [
        6.91,
        6.91,
        6.91,
        6.91,
        6.91,
        6.91,
        6.91,
        6.88,
        6.87,
        6.84,
        6.86,
        6.88,
        6.9,
        6.9,
        6.9,
        6.9,
        6.91,
        6.88,
        6.87,
        6.87,
        6.9,
        6.96,
        6.89,
        6.87,
        6.9,
        6.89,
        6.88,
        6.89,
        6.9,
        6.91
      ],
      "updated": "2026-03-27T03:52:22.667754"
    },
    "nat_gas": {
      "current": 2.927000045776367,
      "day_change_pct": -0.85,
      "war_change_pct": -1.11,
      "dates": [
        "02/12",
        "02/13",
        "02/17",
        "02/18",
        "02/19",
        "02/20",
        "02/23",
        "02/24",
        "02/25",
        "02/26",
        "02/27",
        "03/02",
        "03/03",
        "03/04",
        "03/05",
        "03/06",
        "03/09",
        "03/10",
        "03/11",
        "03/12",
        "03/13",
        "03/16",
        "03/17",
        "03/18",
        "03/19",
        "03/20",
        "03/23",
        "03/24",
        "03/25",
        "03/26"
      ],
      "prices": [
        3.22,
        3.24,
        3.03,
        3.01,
        3.0,
        3.05,
        2.98,
        2.91,
        2.97,
        2.83,
        2.86,
        2.96,
        3.05,
        2.92,
        3.0,
        3.19,
        3.12,
        3.02,
        3.21,
        3.23,
        3.13,
        3.02,
        3.03,
        3.07,
        3.17,
        3.1,
        2.89,
        2.94,
        2.95,
        2.93
      ],
      "updated": "2026-03-27T03:52:22.747929"
    }
  },
  "stocks": {
    "601872": {
      "name": "招商轮船",
      "price": 16.9,
      "change_pct": 1.26,
      "high": 17.1,
      "low": 16.3,
      "volume": 771046
    },
    "600026": {
      "name": "中远海能",
      "price": 23.67,
      "change_pct": -0.96,
      "high": 24.19,
      "low": 22.7,
      "volume": 599107
    },
    "601975": {
      "name": "招商南油",
      "price": 4.44,
      "change_pct": null,
      "high": 4.55,
      "low": 4.39,
      "volume": 1570359
    },
    "600938": {
      "name": "中国海油",
      "price": 40.6,
      "change_pct": -0.81,
      "high": 41.41,
      "low": 40.37,
      "volume": 318571
    },
    "601857": {
      "name": "中国石油",
      "price": 11.94,
      "change_pct": null,
      "high": 12.04,
      "low": 11.83,
      "volume": 1154057
    },
    "600028": {
      "name": "中国石化",
      "price": null,
      "error": "HTTPSConnectionPool(host='push2.eastmoney.com', port=443): Max retries exceeded with url: /api/qt/stock/get?secid=1.600028&fields=f43,f44,f45,f46,f47,f48,f50,f57,f58,f60,f170,f171 (Caused by NewConnectionError(\"HTTPSConnection(host='push2.eastmoney.com', port=443): Failed to establish a new connection: [Errno 101] Network is unreachable\"))"
    },
    "603619": {
      "name": "中曼石油",
      "price": 34.63,
      "change_pct": -0.94,
      "high": 35.28,
      "low": 34.08,
      "volume": 165684
    },
    "600759": {
      "name": "洲际油气",
      "price": 5.99,
      "change_pct": -3.23,
      "high": 6.16,
      "low": 5.91,
      "volume": 2941938
    },
    "601808": {
      "name": "中海油服",
      "price": 16.4,
      "change_pct": -1.8,
      "high": 16.7,
      "low": 16.2,
      "volume": 202918
    },
    "002353": {
      "name": "杰瑞股份",
      "price": 98.96,
      "change_pct": 0.71,
      "high": 99.4,
      "low": 96.15,
      "volume": 67908
    },
    "600803": {
      "name": "新奥股份",
      "price": 22.24,
      "change_pct": 0.45,
      "high": 22.62,
      "low": 21.81,
      "volume": 85452
    },
    "600256": {
      "name": "广汇能源",
      "price": 6.92,
      "change_pct": 0.44,
      "high": 7.05,
      "low": 6.8,
      "volume": 1464708
    },
    "601919": {
      "name": "中远海控",
      "price": 15.14,
      "change_pct": -0.79,
      "high": 15.25,
      "low": 15.06,
      "volume": 418281
    },
    "600760": {
      "name": "中航沈飞",
      "price": 47.76,
      "change_pct": null,
      "high": 47.83,
      "low": 46.89,
      "volume": 51895
    },
    "600893": {
      "name": "航发动力",
      "price": 48.16,
      "change_pct": 0.33,
      "high": 48.25,
      "low": 46.8,
      "volume": 178212
    },
    "600150": {
      "name": "中国船舶",
      "price": null,
      "error": "HTTPSConnectionPool(host='push2.eastmoney.com', port=443): Max retries exceeded with url: /api/qt/stock/get?secid=1.600150&fields=f43,f44,f45,f46,f47,f48,f50,f57,f58,f60,f170,f171 (Caused by NewConnectionError(\"HTTPSConnection(host='push2.eastmoney.com', port=443): Failed to establish a new connection: [Errno 101] Network is unreachable\"))"
    },
    "600547": {
      "name": "山东黄金",
      "price": 38.57,
      "change_pct": 1.42,
      "high": 38.81,
      "low": 37.02,
      "volume": 455160
    },
    "600988": {
      "name": "赤峰黄金",
      "price": 39.46,
      "change_pct": 5.79,
      "high": 39.68,
      "low": 36.65,
      "volume": 428174
    },
    "600489": {
      "name": "中金黄金",
      "price": 25.56,
      "change_pct": 2.08,
      "high": 25.57,
      "low": 24.6,
      "volume": 380183
    },
    "601088": {
      "name": "中国神华",
      "price": 47.39,
      "change_pct": -0.63,
      "high": 48.03,
      "low": 47.18,
      "volume": 118955
    }
  },
  "sectors": {
    "航运": {
      "change_pct": -1.03
    },
    "石油": {
      "change_pct": null
    },
    "天然气": {
      "change_pct": null,
      "error": "HTTPSConnectionPool(host='push2.eastmoney.com', port=443): Read timed out. (read timeout=10)"
    },
    "军工": {
      "change_pct": 0.68
    },
    "黄金": {
      "change_pct": null,
      "error": "HTTPSConnectionPool(host='push2.eastmoney.com', port=443): Max retries exceeded with url: /api/qt/stock/get?secid=90.BK0473&fields=f43,f170,f171 (Caused by NewConnectionError(\"HTTPSConnection(host='push2.eastmoney.com', port=443): Failed to establish a new connection: [Errno 101] Network is unreachable\"))"
    }
  },
  "news": [
    {
      "source": "BBC中文",
      "title": "伊朗外長：我們沒有和美國談判",
      "link": "https://www.bbc.com/zhongwen/articles/cnv834q4prno/trad?at_medium=RSS&at_campaign=rss",
      "published": "Thu, 26 Mar 2026 07:25:18 GMT",
      "summary": "特朗普表示，他正在與伊朗「正確的人」對話，但德黑蘭方面則稱並未進行任何此類談判。",
      "lang": "zh"
    },
    {
      "source": "BBC中文",
      "title": "分析：伊朗拒絕與美國談判，反映不信任",
      "link": "https://www.bbc.com/zhongwen/articles/cgld9rj5w8yo/trad?at_medium=RSS&at_campaign=rss",
      "published": "Thu, 26 Mar 2026 07:34:17 GMT",
      "summary": "但這並不意味著大門已經關閉，因為伊朗的強硬立場更多的可能是為了設定條件，而不是拒絕外交途徑。",
      "lang": "zh"
    },
    {
      "source": "BBC中文",
      "title": "從藥劑師到思鄉博主：看伊朗戰爭的平民代價",
      "link": "https://www.bbc.com/zhongwen/articles/czjw78z3mpvo/trad?at_medium=RSS&at_campaign=rss",
      "published": "Tue, 24 Mar 2026 05:55:46 GMT",
      "summary": "隨著美國和以色列對伊朗的戰爭持續，平民死傷人數正急劇攀升。",
      "lang": "zh"
    },
    {
      "source": "BBC中文",
      "title": "特朗普尋求推遲訪問中國 稱需坐鎮指揮對伊朗戰爭",
      "link": "https://www.bbc.com/zhongwen/articles/c33j36nrx7ro/trad?at_medium=RSS&at_campaign=rss",
      "published": "Wed, 18 Mar 2026 09:03:02 GMT",
      "summary": "美國總統特朗普（Donald Trump）週一表示，他計劃將原定於3月底進行的訪華行程推遲約一個月，以便他能集中精力處理中東戰爭。",
      "lang": "zh"
    },
    {
      "source": "BBC中文",
      "title": "伊朗戰爭激化：中國有何盤算？如何影響習特會談？",
      "link": "https://www.bbc.com/zhongwen/articles/cn5gn0zrd0vo/trad?at_medium=RSS&at_campaign=rss",
      "published": "Thu, 12 Mar 2026 17:37:54 GMT",
      "summary": "中國是伊朗最大的石油買家，長期以來與伊朗保持密切外交關係。如今德黑蘭遭受攻擊，中國強烈譴責美國空襲，但對伊朗的支持是否僅止於口頭？BBC駐中國記者碧嘉蘭以及中伊關係專家威廉·菲格羅，一同剖析最新局勢。",
      "lang": "zh"
    },
    {
      "source": "BBC中文",
      "title": "分析：美伊談判小窗口已開，但迅速結束戰爭仍不太可能",
      "link": "https://www.bbc.com/zhongwen/articles/c62j784n11zo/trad?at_medium=RSS&at_campaign=rss",
      "published": "Wed, 25 Mar 2026 03:59:43 GMT",
      "summary": "美國總統特朗普表示，美方已經在與伊朗的一位「最高層人士」接觸，但德黑蘭否認任何談判已經開始。",
      "lang": "zh"
    },
    {
      "source": "BBC中文",
      "title": "分析：戰爭持續越久，美國和伊朗就會更加陷入欲罷不能的境地",
      "link": "https://www.bbc.com/zhongwen/articles/cy01g4kpkk7o/trad?at_medium=RSS&at_campaign=rss",
      "published": "Tue, 24 Mar 2026 04:21:55 GMT",
      "summary": "特朗普的選項越來越少。進一步升級可能成為無止境的破壞循環，卻缺乏明確戰略利益，使剩下的只會是最極端的方案。伊朗局勢同樣艱難。該國在衝突前就已面臨經濟壓力和廣泛民怨，若後退將顯得軟弱。",
      "lang": "zh"
    },
    {
      "source": "BBC中文",
      "title": "為何海灣國家尚未報復伊朗？",
      "link": "https://www.bbc.com/zhongwen/articles/c0lep1nexx3o/trad?at_medium=RSS&at_campaign=rss",
      "published": "Mon, 23 Mar 2026 08:11:31 GMT",
      "summary": "專家表示，海灣國家不願直接捲入戰爭，但不太可能接受無限期地遭受攻擊。",
      "lang": "zh"
    },
    {
      "source": "德国之声",
      "title": "德语媒体：伊朗战争中的大国博弈",
      "link": "https://www.dw.com/zh/德语媒体：伊朗战争中的大国博弈/a-76548141?maca=chi-rss-chi-all-1127-xml-mrss",
      "published": "Thu, 26 Mar 2026 15:10:00 GMT",
      "summary": "《柏林日报》发表评论称，伊朗战争绝不仅仅是一场地区性军事冲突，更是超级大国间围绕资源控制和势力范围的一场博弈，而无论这场大国博弈的结局如何，欧洲恐怕都只能扮演看客的角色。《商报》评论则分析了中国在霍尔木兹危机中表现出较强“战略定力”的原因。",
      "lang": "zh"
    },
    {
      "source": "德国之声",
      "title": "德防长访日、新、澳：扩大印太影响力 加强军备合作",
      "link": "https://www.dw.com/zh/德防长访日、新、澳：扩大印太影响力-加强军备合作/a-76544215?maca=chi-rss-chi-all-1127-xml-mrss",
      "published": "Thu, 26 Mar 2026 12:27:00 GMT",
      "summary": "德国防长皮斯托里乌斯在访问日本、新加坡后，在澳大利亚继续推进军备合作。他表示，特别在中东战争背景下，凸显军备合作多样化的必要性，以避免过度的依赖性——无论是供应链依赖中国，还是特定武器系统依赖美国。",
      "lang": "zh"
    },
    {
      "source": "德国之声",
      "title": "川普宣布五月訪中國與習近平見面",
      "link": "https://www.dw.com/zh/川普宣布五月訪中國與習近平見面/a-76536384?maca=chi-rss-chi-all-1127-xml-mrss",
      "published": "Thu, 26 Mar 2026 07:34:00 GMT",
      "summary": "美國本周宣布，川普將於5月14日至15日訪問中國，並與習近平舉行「具里程碑意義」的高層會晤。這將是川普睽違八年再度踏上中國，外界亦關注在國際局勢動盪之際，此次峰會是否意味著伊朗戰事將走向明朗。",
      "lang": "zh"
    },
    {
      "source": "德国之声",
      "title": "利用伊朗战争施压：中共对台“认知战”升级？",
      "link": "https://www.dw.com/zh/利用伊朗战争施压：中共对台-认知战-升级？/a-76529620?maca=chi-rss-chi-all-1127-xml-mrss",
      "published": "Wed, 25 Mar 2026 15:18:00 GMT",
      "summary": "伊朗战争可能削弱针台湾对中国的防御力量吗？中国对台湾的“认知战”是否会因为这场战争而升级？",
      "lang": "zh"
    },
    {
      "source": "德国之声",
      "title": "德语媒体：中国将成为伊朗战争的赢家？",
      "link": "https://www.dw.com/zh/德语媒体：中国将成为伊朗战争的赢家？/a-76528783?maca=chi-rss-chi-all-1127-xml-mrss",
      "published": "Wed, 25 Mar 2026 14:33:00 GMT",
      "summary": "《经济周刊》长篇评论认为，持续已经近一个月的伊朗战争，虽然尚未分出胜负。但从战略层面上而言，中国很有可能成为最后的赢家。《每日镜报》则分析了全球油价飙升、航运受阻的情况下，中国为何能表现出较强抗压能力的原因。",
      "lang": "zh"
    },
    {
      "source": "德国之声",
      "title": "美国递交十五点停火计划 伊朗坚称“绝不妥协”",
      "link": "https://www.dw.com/zh/美国递交十五点停火计划-伊朗坚称-绝不妥协/a-76526736?maca=chi-rss-chi-all-1127-xml-mrss",
      "published": "Wed, 25 Mar 2026 13:57:00 GMT",
      "summary": "尽管美国总统特朗普表示美伊正在进行谈判，并已通过巴基斯坦向德黑兰转达了一份包含15项条件的停火协议，但伊朗军方与外交部周三同步发表强硬声明，否认存在任何形式的对话。",
      "lang": "zh"
    },
    {
      "source": "德国之声",
      "title": "中国船东货船通过霍尔木兹海峡“安全走廊”",
      "link": "https://www.dw.com/zh/中国船东货船通过霍尔木兹海峡-安全走廊/a-76522916?maca=chi-rss-chi-all-1127-xml-mrss",
      "published": "Wed, 25 Mar 2026 12:06:00 GMT",
      "summary": "伊朗开辟霍尔木兹海峡“安全走廊”10天后，首艘中国船东的货船通过这一水域。摩根大通银行大宗商品分析师指出，通过该海峡的大部分石油流向亚洲，主要是中国。",
      "lang": "zh"
    },
    {
      "source": "德国之声",
      "title": "伊朗监控网络反遭利用:以色列如何将其转为暗杀利器",
      "link": "https://www.dw.com/zh/伊朗监控网络反遭利用-以色列如何将其转为暗杀利器/a-76518670?maca=chi-rss-chi-all-1127-xml-mrss",
      "published": "Wed, 25 Mar 2026 10:04:00 GMT",
      "summary": "用魔法打败魔法。以色列军方在刺杀伊朗最高领袖的行动中通过劫持该国街头监控摄像头所发挥的作用，凸显了在战争时期，监控系统正日益成为兵家必争之地。",
      "lang": "zh"
    },
    {
      "source": "FT中文网",
      "title": "法拉利通过空运向中东富豪交付定制超跑",
      "link": "https://www.ftchinese.com/story/001109296",
      "published": "Thu, 26 Mar 2026 16:00:00 GMT",
      "summary": "行业人士称，伊朗战争导致的运费上涨意味着，空运一辆豪车至海湾地区的费用已达海运的四到五倍，但急于拿到定制豪车的买家仍然愿意支付溢价。",
      "lang": "zh"
    },
    {
      "source": "FT中文网",
      "title": "伊朗的最先进导弹去了哪里？",
      "link": "https://www.ftchinese.com/story/001109295",
      "published": "Thu, 26 Mar 2026 16:00:00 GMT",
      "summary": "伊朗与美以联军在海湾地区进行的战争已经接近一个月，但该国去年所展示的最新型导弹至今仍未投入实战。",
      "lang": "zh"
    },
    {
      "source": "FT中文网",
      "title": "欧洲议会批准美欧贸易协定",
      "link": "https://www.ftchinese.com/story/001109294",
      "published": "Thu, 26 Mar 2026 16:00:00 GMT",
      "summary": "唐纳德•特朗普吞并格陵兰的威胁曾导致欧洲议会推迟批准该协定。",
      "lang": "zh"
    },
    {
      "source": "FT中文网",
      "title": "中东战火推高化肥价格 俄罗斯受益",
      "link": "https://www.ftchinese.com/story/001109284",
      "published": "Wed, 25 Mar 2026 16:00:00 GMT",
      "summary": "随着中东供应大国纷纷停产，而且难以通过霍尔木兹海峡发运出口化肥，亲俄的匈牙利政府要求欧盟放宽针对俄罗斯化肥的制裁措施。",
      "lang": "zh"
    },
    {
      "source": "FT中文网",
      "title": "特朗普考虑邀请卢卡申科访美",
      "link": "https://www.ftchinese.com/story/001109264",
      "published": "Mon, 23 Mar 2026 16:00:00 GMT",
      "summary": "白俄罗斯总统声称特朗普已邀请他前往海湖庄园讨论“大交易”。此前美国以放松制裁为条件，争取到白俄罗斯释放大批政治犯。",
      "lang": "zh"
    },
    {
      "source": "FT中文网",
      "title": "特朗普宣布暂缓攻击伊朗能源设施后市场反弹",
      "link": "https://www.ftchinese.com/story/001109263",
      "published": "Mon, 23 Mar 2026 16:00:00 GMT",
      "summary": "美国总统称，美伊就“全面彻底解决敌对行动”进行了“非常好的、富有成效的对话”，针对发电厂和能源基础设施的军事打击将延后五天。",
      "lang": "zh"
    },
    {
      "source": "FT中文网",
      "title": "古巴几天里两次全国停电",
      "link": "https://www.ftchinese.com/story/001109256",
      "published": "Sun, 22 Mar 2026 16:00:00 GMT",
      "summary": "美国的能源封锁给哈瓦那政权带来越来越大压力。上周载有俄罗斯燃料的两艘船舶有一艘中途改道，不再以古巴为目的地。",
      "lang": "zh"
    },
    {
      "source": "FT中文网",
      "title": "李强：中国致力成为“稳定性港湾”",
      "link": "https://www.ftchinese.com/story/001109255",
      "published": "Sun, 22 Mar 2026 16:00:00 GMT",
      "summary": "美国深陷伊朗战争泥潭之际，中国总理在年度中国发展高层论坛上告诉70多位全球顶级高管，中国拥有无可比拟的供应链和可预测的商业环境。",
      "lang": "zh"
    },
    {
      "source": "BBC中东",
      "title": "Trump's Iran strategy is to pursue two off-ramps at once",
      "link": "https://www.bbc.com/news/articles/c15d980nyw1o?at_medium=RSS&at_campaign=rss",
      "published": "Thu, 26 Mar 2026 02:00:53 GMT",
      "summary": "The White House insists the president is dictating events, but even some Republicans are frustrated by mixed messaging about his war aims.",
      "lang": "en"
    }
  ],
  "shipping": {
    "hormuz": {
      "dates": [
        "2/26",
        "2/27",
        "2/28",
        "3/1",
        "3/2",
        "3/3",
        "3/4",
        "3/5",
        "3/6",
        "3/7",
        "3/8",
        "3/9",
        "3/10",
        "3/11",
        "3/12",
        "3/13",
        "3/14",
        "3/15",
        "3/16",
        "3/17",
        "3/18",
        "3/19",
        "3/20",
        "3/21",
        "3/22",
        "3/23",
        "3/24",
        "3/25",
        "3/26",
        "3/27"
      ],
      "transits": [
        35,
        33,
        18,
        7,
        5,
        6,
        4,
        3,
        4,
        3,
        2,
        1,
        2,
        2,
        3,
        4,
        0,
        0,
        0,
        0,
        0,
        0,
        0,
        0,
        0,
        0,
        0,
        0,
        0,
        0
      ]
    },
    "vlcc": {
      "dates": [
        "1/3",
        "1/10",
        "1/17",
        "1/24",
        "1/31",
        "2/7",
        "2/14",
        "2/21",
        "2/28",
        "3/2",
        "3/4",
        "3/6",
        "3/8",
        "3/10",
        "3/13"
      ],
      "rates": [
        29,
        32,
        45,
        55,
        80,
        95,
        110,
        123,
        200,
        280,
        350,
        420,
        466,
        486,
        349
      ]
    },
    "routes": {
      "labels": [
        "霍尔木兹海峡",
        "苏伊士运河",
        "曼德海峡",
        "好望角"
      ],
      "pre_war": [
        33,
        55,
        23,
        45
      ],
      "current": [
        0,
        23,
        21,
        69
      ],
      "date_label": "3月27日"
    },
    "freshness": {
      "hormuz_last_date": "2026-03-27",
      "hormuz_stale_days": 0,
      "hormuz_is_estimate": true,
      "vlcc_last_date": "2026-03-13",
      "vlcc_stale_days": 14,
      "vlcc_is_scraped": false,
      "routes_date": "2026-03-27"
    }
  },
  "meta": {
    "report_date": "2026.03.27",
    "report_date_cn": "2026年03月27日",
    "war_day": 28,
    "war_start": "2026-02-28",
    "generated_at": "2026-03-27T11:53:54.121042+08:00",
    "generated_at_cn": "2026-03-27 11:53:54 北京时间"
  },
  "history": [
    {
      "date": "2026-03-17",
      "brent": 102.5999984741211,
      "wti": 95.93000030517578,
      "gold": 5009.7998046875,
      "usd_cny": 6.868899822235107
    },
    {
      "date": "2026-03-17",
      "brent": 104.30999755859375,
      "wti": 97.9000015258789,
      "gold": 5016.10009765625,
      "usd_cny": 6.888500213623047
    },
    {
      "date": "2026-03-17",
      "brent": 103.83000183105469,
      "wti": 97.30999755859375,
      "gold": 5010.2001953125,
      "usd_cny": 6.888500213623047
    },
    {
      "date": "2026-03-17",
      "brent": 103.70999908447266,
      "wti": 97.25,
      "gold": 5014.89990234375,
      "usd_cny": 6.888400077819824
    },
    {
      "date": "2026-03-17",
      "brent": 103.56999969482422,
      "wti": 96.31999969482422,
      "gold": 5026.0,
      "usd_cny": 6.883399963378906
    },
    {
      "date": "2026-03-18",
      "brent": 103.41999816894531,
      "wti": 96.20999908447266,
      "gold": 5001.0,
      "usd_cny": 6.880199909210205
    },
    {
      "date": "2026-03-18",
      "brent": 103.41999816894531,
      "wti": 96.20999908447266,
      "gold": 5001.0,
      "usd_cny": 6.879799842834473
    },
    {
      "date": "2026-03-18",
      "brent": 102.8499984741211,
      "wti": 94.02999877929688,
      "gold": 4993.5,
      "usd_cny": 6.872300148010254
    },
    {
      "date": "2026-03-18",
      "brent": 109.52999877929688,
      "wti": 98.2300033569336,
      "gold": 4873.89990234375,
      "usd_cny": 6.872099876403809
    },
    {
      "date": "2026-03-18",
      "brent": 109.7699966430664,
      "wti": 98.55999755859375,
      "gold": 4866.2998046875,
      "usd_cny": 6.872099876403809
    },
    {
      "date": "2026-03-20",
      "brent": 103.30000305175781,
      "wti": 94.0,
      "gold": 4699.0,
      "usd_cny": 6.882400035858154
    },
    {
      "date": "2026-03-21",
      "brent": 106.7699966430664,
      "wti": 98.08999633789062,
      "gold": 4492.0,
      "usd_cny": 6.885200023651123
    },
    {
      "date": "2026-03-22",
      "brent": 106.41000366210938,
      "wti": 98.2300033569336,
      "gold": 4574.89990234375,
      "usd_cny": 6.885200023651123
    },
    {
      "date": "2026-03-23",
      "brent": 107.95999908447266,
      "wti": 99.19000244140625,
      "gold": 4348.0,
      "usd_cny": 6.9085001945495605
    },
    {
      "date": "2026-03-24",
      "brent": 103.81999969482422,
      "wti": 91.4800033569336,
      "gold": 4362.0,
      "usd_cny": 6.8933000564575195
    },
    {
      "date": "2026-03-25",
      "brent": 99.61000061035156,
      "wti": 88.77999877929688,
      "gold": 4574.60009765625,
      "usd_cny": 6.890399932861328
    },
    {
      "date": "2026-03-26",
      "brent": 98.45999908447266,
      "wti": 91.66000366210938,
      "gold": 4514.2001953125,
      "usd_cny": 6.901199817657471
    },
    {
      "date": "2026-03-27",
      "brent": 100.86000061035156,
      "wti": 93.52999877929688,
      "gold": 4434.10009765625,
      "usd_cny": 6.913000106811523
    }
  ]
}